free_search/__init__.py
free_search/db.py
free_search-0.3.0.dist-info/LICENSE
free_search-0.3.0.dist-info/METADATA
free_search-0.3.0.dist-info/WHEEL
free_search-0.3.0.dist-info/top_level.txt
free_search-0.3.0.dist-info/RECORD
